README.rst
setup.py
bin/__init__.py
bin/datafaker
bin/datafaker.cmd
datafaker/__init__.py
datafaker/__main__.py
datafaker/cli.py
datafaker/compat.py
datafaker/constant.py
datafaker/drivers.py
datafaker/exceptions.py
datafaker/fakedata.py
datafaker/multithreading.py
datafaker/reg.py
datafaker/testutils.py
datafaker/utils.py
datafaker.egg-info/PKG-INFO
datafaker.egg-info/SOURCES.txt
datafaker.egg-info/dependency_links.txt
datafaker.egg-info/requires.txt
datafaker.egg-info/top_level.txt
datafaker/dbs/__init__.py
datafaker/dbs/basedb.py
datafaker/dbs/esdb.py
datafaker/dbs/filedb.py
datafaker/dbs/hbasedb.py
datafaker/dbs/hivedb.py
datafaker/dbs/kafkadb.py
datafaker/dbs/mysqldb.py
datafaker/dbs/rdbdb.py